tkinter_files_folders/LICENSE
tkinter_files_folders/README.MD
tkinter_files_folders/__init__.py
tkinter_files_folders/requirements.txt
tkinter_files_folders/thirdparty.json
tkinter_files_folders-0.11.dist-info/LICENSE.rst
tkinter_files_folders-0.11.dist-info/METADATA
tkinter_files_folders-0.11.dist-info/WHEEL
tkinter_files_folders-0.11.dist-info/top_level.txt
tkinter_files_folders-0.11.dist-info/RECORD
