Metadata-Version: 2.1
Name: tkinter-files-folders
Version: 0.11
Summary: Some tkinter functions for selecting files/folders
Home-page: https://github.com/hansalemaos/tkinter_files_folders
Author: Johannes Fischer
Author-email: aulasparticularesdealemaosp@gmail.com
License: MIT
Keywords: tkinter,files,folders
Classifier: Development Status :: 4 - Beta
Classifier: Programming Language :: Python :: 3 :: Only
Classifier: Programming Language :: Python :: 3.10
Classifier: Topic :: Software Development :: Libraries :: Python Modules
Classifier: Topic :: Utilities
License-File: LICENSE.rst
